Planet3D/__init__.py
Planet3D-0.3.0.dist-info/LICENSE
Planet3D-0.3.0.dist-info/METADATA
Planet3D-0.3.0.dist-info/WHEEL
Planet3D-0.3.0.dist-info/top_level.txt
Planet3D-0.3.0.dist-info/RECORD
