Metadata-Version: 2.1
Name: Planet3D
Version: 0.3.0
Summary: A 3D representation of the solar system using Pygame and OpenGL
Home-page: https://github.com/ishanoshada/Planet3D
Author: Ishan Oshada
Author-email: ishan.kodithuwakku@gmail.com
Classifier: Programming Language :: Python :: 3
Classifier: License :: OSI Approved :: MIT License
Classifier: Operating System :: OS Independent
License-File: LICENSE
Requires-Dist: pygame
Requires-Dist: PyOpenGL
